.gitignore
README
setup.py
mailcat/__init__.py
mailcat/__main__.py
mailcat/__version__.py
mailcat/_backports.py
mailcat/mailfile.py
mailcat/message.py
mailcat/utils.py
mailcat.egg-info/PKG-INFO
mailcat.egg-info/SOURCES.txt
mailcat.egg-info/dependency_links.txt
mailcat.egg-info/entry_points.txt
mailcat.egg-info/pbr.json
mailcat.egg-info/requires.txt
mailcat.egg-info/top_level.txt