Metadata-Version: 1.1
Name: mailcat
Version: 0.2
Summary: Console viewer for MIME mail files
Home-page: https://python.org/pypi/mailcat
Author: Andrey Golovizin
Author-email: ag@sologoc.com
License: GPL-3+
Platform: platform-independent
Classifier: Development Status :: 3 - Alpha
Classifier: Environment :: Console
Classifier: License :: OSI Approved :: GNU General Public License (GPL)
Classifier: Operating System :: OS Independent
Classifier: Programming Language :: Python
